[
  {
    "id": "1640995200000",
    "timestamp": "2024-01-01T12:00:00.000Z",
    "age": "26-35",
    "gender": "masculino",
    "education": "universitario",
    "techExperience": "intermedio",
    "devices": ["Smartphone", "Laptop/PC", "Smart TV", "Tablet"],
    "internetProvider": "Movistar",
    "routerAge": "1-3",
    "wifiPassword": "simple",
    "passwordManager": "no",
    "twoFactor": "algunas",
    "softwareUpdates": "mensualmente",
    "publicWifi": "navegacion-basica",
    "privacyConcern": "algo-preocupado",
    "dataSharing": "a-veces",
    "convenienceVsPrivacy": "balance",
    "trustInTech": "algo",
    "securityKnowledge": "intermedio",
    "threatAwareness": ["Phishing", "Malware", "Ransomware"],
    "securityMeasures": ["Antivirus actualizado", "Copias de seguridad regulares"],
    "additionalComments": "Me preocupa la seguridad pero a veces es complicado implementar todas las medidas."
  },
  {
    "id": "1640995260000",
    "timestamp": "2024-01-01T12:01:00.000Z",
    "age": "18-25",
    "gender": "femenino",
    "education": "tecnico",
    "techExperience": "principiante",
    "devices": ["Smartphone", "Laptop/PC"],
    "internetProvider": "Claro",
    "routerAge": "mas-5",
    "wifiPassword": "predeterminada",
    "passwordManager": "no-se-que-es",
    "twoFactor": "no",
    "softwareUpdates": "raramente",
    "publicWifi": "todo",
    "privacyConcern": "poco-preocupado",
    "dataSharing": "frecuentemente",
    "convenienceVsPrivacy": "conveniencia",
    "trustInTech": "mucho",
    "securityKnowledge": "principiante",
    "threatAwareness": ["Ninguna"],
    "securityMeasures": ["Ninguna"],
    "additionalComments": "No sabía que había tantas amenazas. Esta encuesta me ha hecho reflexionar."
  }
]
